symbolic/common.py
symbolic/symcache.py
symbolic/exceptions.py
symbolic/_lowlevel.py
symbolic/utils.py
symbolic/_compat.py
symbolic/debuginfo.py
symbolic/demangle.py
symbolic/_lowlevel__ffi.py
symbolic/__init__.py
symbolic/_lowlevel__lib.so
symbolic_python-0.1.0.dist-info/DESCRIPTION.rst
symbolic_python-0.1.0.dist-info/METADATA
symbolic_python-0.1.0.dist-info/RECORD
symbolic_python-0.1.0.dist-info/WHEEL
symbolic_python-0.1.0.dist-info/metadata.json
symbolic_python-0.1.0.dist-info/top_level.txt
