Metadata-Version: 2.0
Name: symbolic-python
Version: 0.1.0
Summary: UNKNOWN
Home-page: UNKNOWN
Author: UNKNOWN
Author-email: UNKNOWN
License: UNKNOWN
Platform: any
Requires-Dist: milksnake
